image_explorer/__init__.py
image_explorer/image_explorer.py
image_explorer/utils.py
image_explorer/public/css/image_explorer.css
image_explorer/public/images/hotspot-sprite.png
image_explorer/public/js/image_explorer.js
image_explorer/public/js/image_explorer_edit.js
image_explorer/public/js/ooyala_player.js
image_explorer/templates/html/image_explorer.html
image_explorer/templates/html/image_explorer_edit.html
image_explorer/translations/config.yaml
xblock_image_explorer-3.0.2.dist-info/licenses/LICENSE
xblock_image_explorer-3.0.2.dist-info/METADATA
xblock_image_explorer-3.0.2.dist-info/WHEEL
xblock_image_explorer-3.0.2.dist-info/entry_points.txt
xblock_image_explorer-3.0.2.dist-info/top_level.txt
xblock_image_explorer-3.0.2.dist-info/RECORD
