Metadata-Version: 2.4
Name: xblock-image-explorer
Version: 3.0.2
Summary: XBlock - Image Explorer
Home-page: https://github.com/openedx/xblock-image-explorer
Classifier: Programming Language :: Python
Classifier: Programming Language :: Python :: 3.11
Classifier: Programming Language :: Python :: 3.12
Classifier: Framework :: Django
Classifier: Framework :: Django :: 4.2
Classifier: Framework :: Django :: 5.2
Requires-Python: >=3.11
License-File: LICENSE
Requires-Dist: parsel==v1.6
Requires-Dist: xblock[django]
Dynamic: classifier
Dynamic: description
Dynamic: description-content-type
Dynamic: home-page
Dynamic: license-file
Dynamic: requires-dist
Dynamic: requires-python
Dynamic: summary
